btbricks/__init__.py
btbricks/bt.py
btbricks/bthub.py
btbricks/ctrl_plus.py
btbricks-0.2.4.dist-info/licenses/LICENSE
tests/__init__.py
tests/test_bthub.py
tests/test_constants.py
tests/test_imports.py
tests/test_precommit_checks.py
btbricks-0.2.4.dist-info/METADATA
btbricks-0.2.4.dist-info/WHEEL
btbricks-0.2.4.dist-info/top_level.txt
btbricks-0.2.4.dist-info/RECORD
