Metadata-Version: 2.4
Name: btbricks
Version: 0.2.4
Summary: A MicroPython Bluetooth library for remote controlling LEGO hubs via BLE
Home-page: https://github.com/antonvh/btbricks
Author: Anton Vanhoucke
Author-email: Anton Vanhoucke <anton@antonsmindstorms.com>
License: MIT
Project-URL: Homepage, https://github.com/antonvh/btbricks
Project-URL: Documentation, https://docs.antonsmindstorms.com/en/latest/Software/btbricks/docs/index.html
Project-URL: Repository, https://github.com/antonvh/btbricks.git
Project-URL: Issues, https://github.com/antonvh/btbricks/issues
Keywords: micropython,bluetooth,ble,lego,hub,control
Classifier: Development Status :: 4 - Beta
Classifier: Intended Audience :: Developers
Classifier: Intended Audience :: Education
Classifier: License :: OSI Approved :: MIT License
Classifier: Operating System :: OS Independent
Classifier: Programming Language :: Python :: Implementation :: MicroPython
Classifier: Topic :: Software Development :: Libraries :: Python Modules
Classifier: Topic :: System :: Hardware
Requires-Python: >=3.7
License-File: LICENSE
Provides-Extra: dev
Requires-Dist: pytest>=7.0; extra == "dev"
Requires-Dist: pytest-asyncio>=0.20.0; extra == "dev"
Requires-Dist: black>=23.0; extra == "dev"
Requires-Dist: flake8>=5.0; extra == "dev"
Requires-Dist: mypy>=1.0; extra == "dev"
Requires-Dist: mpy-cross>=1.20; extra == "dev"
Requires-Dist: requests>=2.28.0; extra == "dev"
Requires-Dist: markdown-link-validator>=0.1.0; extra == "dev"
Provides-Extra: docs
Requires-Dist: sphinx>=4.0; extra == "docs"
Requires-Dist: sphinx-rtd-theme>=1.0; extra == "docs"
Requires-Dist: sphinx-autodoc-typehints>=1.12; extra == "docs"
Dynamic: author
Dynamic: home-page
Dynamic: license-file
Dynamic: requires-python
